[
    {
        "annotations": [
            {
                "class": "fish",
                "xn": "668.5254595;406.102499377",
                "yn": "222.050197028;179.302565514"
            },
            {
                "class": "fish",
                "xn": "406.102499377;134.180065584",
                "yn": "670.900327918;666.150591083"
            },
            {
                "class": "fish",
                "xn": "713.647959431;469.036512438",
                "yn": "662.588288457;594.904538561"
            },
            {
                "class": "fish",
                "xn": "793.206051414;527.220788664",
                "yn": "441.725525638;444.100394055"
            },
            {
                "class": "fish",
                "xn": "966.571445885;740.958946231",
                "yn": "439.35065722;483.285722942"
            },
            {
                "class": "fish",
                "xn": "980.820656389;695.8364463",
                "yn": "21.3738157567;35.6230262611"
            },
            {
                "class": "fish",
                "xn": "1164.87295874;960.634274841",
                "yn": "153.179012923;219.67532861"
            },
            {
                "class": "fish",
                "xn": "1252.74309018;1067.50335362",
                "yn": "707.710788387;765.895064614"
            },
            {
                "class": "fish",
                "xn": "786.081446162;504.659538699",
                "yn": "919.074077537;920.261511745"
            },
            {
                "class": "fish",
                "xn": "643.589341117;372.854341533",
                "yn": "1010.50651161;1025.94315632"
            },
            {
                "class": "fish",
                "xn": "1128.06249827;957.071972215",
                "yn": "906.012301241;1014.06881423"
            },
            {
                "class": "fish",
                "xn": "1536.53986606;1261.05512964",
                "yn": "786.081446162;821.704472423"
            },
            {
                "class": "fish",
                "xn": "1471.23098458;1240.8687481",
                "yn": "946.385064337;965.384011676"
            },
            {
                "class": "fish",
                "xn": "1791.83822093;1541.2896029",
                "yn": "369.292038907;420.351709881"
            },
            {
                "class": "fish",
                "xn": "689.899275257;429.851183551",
                "yn": "1168.43526136;1176.74730083"
            },
            {
                "class": "fish",
                "xn": "834.766248719;599.654275395",
                "yn": "1340.61322163;1323.9891427"
            },
            {
                "class": "fish",
                "xn": "672.087762126;440.538091429",
                "yn": "1663.59532639;1645.78381326"
            },
            {
                "class": "fish",
                "xn": "643.589341117;403.727630959",
                "yn": "1809.64973406;1775.21414201"
            },
            {
                "class": "fish",
                "xn": "1088.87716938;809.830130336",
                "yn": "1414.23414257;1481.91789246"
            },
            {
                "class": "fish",
                "xn": "1367.92420843;1120.93789302",
                "yn": "1443.91999778;1448.66973462"
            },
            {
                "class": "fish",
                "xn": "1275.30434015;1037.81749841",
                "yn": "1638.65920801;1664.7827606"
            },
            {
                "class": "fish",
                "xn": "1513.9786161;1316.86453745",
                "yn": "1778.77644464;1899.89473393"
            },
            {
                "class": "fish",
                "xn": "450.037565099;212.550723358",
                "yn": "2178.94177297;2233.56374657"
            },
            {
                "class": "fish",
                "xn": "1467.66868196;1200.495985",
                "yn": "2389.11762791;2409.30400946"
            },
            {
                "class": "fish",
                "xn": "1544.85190552;1439.17026095",
                "yn": "2028.13762847;2173.00460193"
            },
            {
                "class": "fish",
                "xn": "1985.38999695;1762.15236572",
                "yn": "1840.52302349;1874.95861554"
            },
            {
                "class": "fish",
                "xn": "2319.0590096;2072.07269419",
                "yn": "2142.1313125;2157.56795721"
            },
            {
                "class": "fish",
                "xn": "2415.2411805;2157.56795721",
                "yn": "2455.6139436;2469.8631541"
            },
            {
                "class": "fish",
                "xn": "2699.03795638;2461.55111464",
                "yn": "2328.55848327;2314.30927276"
            },
            {
                "class": "fish",
                "xn": "2950.77400863;2708.53743005",
                "yn": "2243.06322024;2155.1930888"
            },
            {
                "class": "fish",
                "xn": "3057.64308741;2889.02742978",
                "yn": "1494.97966876;1636.28433959"
            },
            {
                "class": "fish",
                "xn": "2486.48723303;2241.87578603",
                "yn": "1213.5577613;1256.30539281"
            },
            {
                "class": "fish",
                "xn": "2087.5093389;1909.3942076",
                "yn": "903.637432824;1021.19341949"
            },
            {
                "class": "fish",
                "xn": "1914.14394443;1677.8445369",
                "yn": "1022.38085369;1014.06881423"
            },
            {
                "class": "fish",
                "xn": "2213.37736502;2005.5763785",
                "yn": "676.837498961;733.834340979"
            },
            {
                "class": "fish",
                "xn": "1923.6434181;1686.15657636",
                "yn": "523.658486038;565.218683343"
            },
            {
                "class": "fish",
                "xn": "2771.47144311;2495.9867067",
                "yn": "331.294144228;343.168486315"
            },
            {
                "class": "fish",
                "xn": "2956.71117967;2691.91335113",
                "yn": "113.993684036;129.430328749"
            },
            {
                "class": "fish_3",
                "xn": "3568.23979715;3277.31841602",
                "yn": "43.935065722;78.3706577745"
            },
            {
                "class": "fish",
                "xn": "3837.78736253;3572.98953399",
                "yn": "296.858552176;264.797828541"
            },
            {
                "class": "fish",
                "xn": "3496.99374463;3227.44617926",
                "yn": "355.042828402;413.227104629"
            },
            {
                "class": "fish",
                "xn": "3310.56657387;3055.26821899",
                "yn": "1100.75151147;1109.06355093"
            },
            {
                "class": "fish",
                "xn": "3518.36756039;3272.56867919",
                "yn": "1295.4907217;1360.79960317"
            },
            {
                "class": "fish",
                "xn": "3824.72558623;3590.80104712",
                "yn": "1460.54407671;1466.48124775"
            },
            {
                "class": "fish",
                "xn": "3616.92459971;3375.87545534",
                "yn": "1604.22361596;1601.84874754"
            },
            {
                "class": "fish",
                "xn": "3473.24506046;3278.50585023",
                "yn": "1699.21835266;1784.71361568"
            },
            {
                "class": "fish",
                "xn": "3780.79052051;3576.55183662",
                "yn": "1696.84348424;1779.96387885"
            },
            {
                "class": "fish",
                "xn": "3665.60940227;3412.68591581",
                "yn": "1934.33032598;1958.07901015"
            },
            {
                "class": "fish",
                "xn": "3304.62940282;3065.95512687",
                "yn": "2064.94808894;2135.00670725"
            },
            {
                "class": "fish",
                "xn": "3738.042889;3473.24506046",
                "yn": "2291.7480228;2302.43493068"
            },
            {
                "class": "fish",
                "xn": "3886.47216509;3711.91933641",
                "yn": "1779.96387885;1869.0214445"
            },
            {
                "class": "fish",
                "xn": "169.272536134;1.68430384213",
                "yn": "405.917225954;529.713558351"
            }
        ],
        "class": "image",
        "filename": "..\\IMG_6848.jpg"
    }
]
