[
    {
        "annotations": [
            {
                "class": "fish",
                "xn": "342.236206221;305.205412528",
                "yn": "522.014736888;433.021377853"
            },
            {
                "class": "fish",
                "xn": "861.264588779;741.213144712",
                "yn": "241.297429866;207.85026137"
            },
            {
                "class": "fish",
                "xn": "499.31844398;469.45490068",
                "yn": "459.898566824;381.656083377"
            },
            {
                "class": "fish",
                "xn": "579.95001089;452.134045565",
                "yn": "563.823697508;526.19563295"
            },
            {
                "class": "fish",
                "xn": "272.355514898;255.63193065",
                "yn": "597.270866005;523.806549486"
            },
            {
                "class": "fish",
                "xn": "749.574936836;640.274368357",
                "yn": "573.380031364;513.055673898"
            },
            {
                "class": "fish",
                "xn": "806.912939972;791.383897456",
                "yn": "500.512985712;424.659585729"
            },
            {
                "class": "fish",
                "xn": "817.66381556;759.728541558",
                "yn": "719.711393536;654.608869141"
            },
            {
                "class": "fish",
                "xn": "744.199499042;690.445121101",
                "yn": "666.554286461;609.216283325"
            },
            {
                "class": "fish",
                "xn": "704.779621885;588.311803015",
                "yn": "716.12776834;655.206140007"
            },
            {
                "class": "fish",
                "xn": "593.089969943;489.762110124",
                "yn": "693.431475431;633.107117965"
            },
            {
                "class": "fish",
                "xn": "435.410461317;394.198771563",
                "yn": "634.301659697;560.837343178"
            },
            {
                "class": "fish",
                "xn": "467.663088082;371.502478655",
                "yn": "719.711393536;665.359744729"
            },
            {
                "class": "fish",
                "xn": "298.635433002;269.369160568",
                "yn": "669.540640791;604.438116397"
            },
            {
                "class": "fish",
                "xn": "293.259995208;253.242847186",
                "yn": "740.01860298;663.567932131"
            },
            {
                "class": "fish",
                "xn": "166.638571615;81.8261086426",
                "yn": "713.738684876;655.206140007"
            },
            {
                "class": "fish",
                "xn": "145.136820439;83.0206503746",
                "yn": "801.537502178;741.810415578"
            },
            {
                "class": "fish",
                "xn": "518.431111692;376.280645583",
                "yn": "837.971025004;811.6911069"
            },
            {
                "class": "fish",
                "xn": "357.765248737;268.771889702",
                "yn": "827.220149416;766.89579195"
            },
            {
                "class": "fish",
                "xn": "434.215919585;304.010870796",
                "yn": "799.74568958;756.144916362"
            },
            {
                "class": "fish",
                "xn": "573.97730223;514.847486496",
                "yn": "829.011962014;762.117625022"
            },
            {
                "class": "fish",
                "xn": "719.11412267;581.741823489",
                "yn": "845.735546263;820.65016989"
            },
            {
                "class": "fish",
                "xn": "262.799181042;185.153968461",
                "yn": "928.756196637;842.151921067"
            },
            {
                "class": "fish",
                "xn": "398.379667625;305.802683394",
                "yn": "914.421695853;849.319171459"
            },
            {
                "class": "fish",
                "xn": "537.543779404;402.560563687",
                "yn": "883.960881687;860.070047047"
            },
            {
                "class": "fish",
                "xn": "708.363247081;594.284511675",
                "yn": "981.913303712;910.240799791"
            },
            {
                "class": "fish",
                "xn": "613.994450253;525.001091218",
                "yn": "978.329678516;925.769842307"
            },
            {
                "class": "fish",
                "xn": "532.765612476;463.48219202",
                "yn": "1060.15578716;973.551511588"
            },
            {
                "class": "fish",
                "xn": "432.424106987;339.249851891",
                "yn": "1024.3195352;958.022469071"
            },
            {
                "class": "fish",
                "xn": "287.287286548;204.86390704",
                "yn": "1090.01933046;1002.81778402"
            },
            {
                "class": "fish",
                "xn": "154.693154295;72.8670456526",
                "yn": "1116.89651943;1051.79399503"
            },
            {
                "class": "fish",
                "xn": "115.273277139;215.614782628",
                "yn": "1146.16279186;1096.58930998"
            },
            {
                "class": "fish",
                "xn": "219.198407824;130.802319655",
                "yn": "1214.84894145;1156.31639658"
            },
            {
                "class": "fish",
                "xn": "183.362155863;87.2015464367",
                "yn": "1293.68869577;1241.72613042"
            },
            {
                "class": "fish",
                "xn": "421.673231399;328.498976303",
                "yn": "1277.56238238;1196.33354461"
            },
            {
                "class": "fish",
                "xn": "512.458403032;428.840481791",
                "yn": "1225.00254618;1160.49729265"
            },
            {
                "class": "fish",
                "xn": "497.526631382;425.256856595",
                "yn": "1113.31289423;1058.36397456"
            },
            {
                "class": "fish",
                "xn": "627.134409305;575.769114828",
                "yn": "1102.56201864;1017.15228481"
            },
            {
                "class": "fish",
                "xn": "664.762473863;630.718034501",
                "yn": "1171.24816824;1095.39476825"
            },
            {
                "class": "fish",
                "xn": "754.95037463;650.427973079",
                "yn": "1065.53122495;1005.20686749"
            },
            {
                "class": "fish",
                "xn": "919.199862781;814.67746123",
                "yn": "1057.76670369;974.148782454"
            },
            {
                "class": "fish",
                "xn": "874.404547831;776.452125806",
                "yn": "1153.92731312;1087.03297613"
            },
            {
                "class": "fish",
                "xn": "803.329314776;680.888787245",
                "yn": "1192.15264855;1136.00918714"
            },
            {
                "class": "fish",
                "xn": "956.827927339;849.319171459",
                "yn": "1150.94095879;1106.74291471"
            },
            {
                "class": "fish",
                "xn": "966.981532061;829.011962014",
                "yn": "1201.11171154;1167.06727217"
            },
            {
                "class": "fish",
                "xn": "963.995177731;836.776483272",
                "yn": "1250.68519341;1213.65439972"
            },
            {
                "class": "fish",
                "xn": "947.271593483;845.138275397",
                "yn": "1278.15965325;1239.93431783"
            },
            {
                "class": "fish",
                "xn": "332.679872365;245.478325928",
                "yn": "1345.05399024;1292.49415403"
            },
            {
                "class": "fish",
                "xn": "293.857266074;185.751239327",
                "yn": "1377.90388787;1331.31676032"
            },
            {
                "class": "fish",
                "xn": "496.929360516;394.198771563",
                "yn": "1413.74013983;1356.99940756"
            },
            {
                "class": "fish",
                "xn": "376.877916449;256.229201516",
                "yn": "1454.35455872;1447.18730833"
            },
            {
                "class": "fish",
                "xn": "168.430384213;52.5598362084",
                "yn": "1507.5116658;1474.0644973"
            },
            {
                "class": "fish",
                "xn": "145.734091305;40.0171480223",
                "yn": "1643.68942324;1618.00677601"
            },
            {
                "class": "fish",
                "xn": "535.15469594;469.45490068",
                "yn": "1313.99590521;1269.20059026"
            },
            {
                "class": "fish",
                "xn": "665.359744729;582.339094355",
                "yn": "1391.04384692;1313.39863434"
            },
            {
                "class": "fish",
                "xn": "722.100477;649.830702213",
                "yn": "1346.84580284;1278.75692412"
            },
            {
                "class": "fish",
                "xn": "856.486421851;794.967522652",
                "yn": "1330.71948946;1258.44971467"
            },
            {
                "class": "fish",
                "xn": "947.868864349;876.793631295",
                "yn": "1372.52845008;1309.21773828"
            },
            {
                "class": "fish",
                "xn": "802.73204391;743.602228176",
                "yn": "1444.79822487;1353.41578237"
            },
            {
                "class": "fish",
                "xn": "624.745325841;558.448259714",
                "yn": "1510.49802013;1426.88009889"
            },
            {
                "class": "fish",
                "xn": "517.833840826;365.529769995",
                "yn": "1529.01341697;1501.53895714"
            },
            {
                "class": "fish",
                "xn": "317.748100714;201.87755271",
                "yn": "1609.64498388;1575.60054452"
            },
            {
                "class": "fish",
                "xn": "371.502478655;235.324721206",
                "yn": "1615.02042168;1637.11944372"
            },
            {
                "class": "fish",
                "xn": "532.16834161;452.134045565",
                "yn": "1670.56661221;1611.43679648"
            },
            {
                "class": "fish",
                "xn": "688.056037637;618.175346315",
                "yn": "1658.62119489;1571.41964846"
            },
            {
                "class": "fish",
                "xn": "785.411188796;670.137911657",
                "yn": "1650.85667364;1592.92139963"
            },
            {
                "class": "fish",
                "xn": "947.271593483;850.513713191",
                "yn": "1646.07850671;1583.96233664"
            },
            {
                "class": "fish",
                "xn": "942.493426555;836.179212406",
                "yn": "1566.04421066;1500.94168627"
            },
            {
                "class": "fish",
                "xn": "949.660676947;821.844711622",
                "yn": "1706.40286418;1731.48824055"
            },
            {
                "class": "fish",
                "xn": "966.384261195;832.59558721",
                "yn": "1800.771661;1732.08551141"
            },
            {
                "class": "fish",
                "xn": "758.533999826;707.168705349",
                "yn": "1815.10616179;1767.92176337"
            },
            {
                "class": "fish",
                "xn": "676.707891183;611.605366789",
                "yn": "1785.24261849;1697.44380119"
            },
            {
                "class": "fish",
                "xn": "597.868136871;443.174982575",
                "yn": "1770.31084684;1733.28005315"
            },
            {
                "class": "fish",
                "xn": "289.079099146;344.028018819",
                "yn": "1769.11630511;1675.34477914"
            },
            {
                "class": "fish",
                "xn": "158.276779491;104.522401551",
                "yn": "1808.53618226;1742.23911614"
            },
            {
                "class": "fish",
                "xn": "468.260358948;376.280645583",
                "yn": "1799.57711927;1750.60090826"
            },
            {
                "class": "fish",
                "xn": "415.103251873;296.843620404",
                "yn": "1859.90147674;1825.85703738"
            },
            {
                "class": "fish",
                "xn": "669.540640791;553.670092786",
                "yn": "1892.75137437;1840.19153816"
            },
            {
                "class": "fish",
                "xn": "584.728177819;453.925858164",
                "yn": "1974.57748301;1928.58762633"
            },
            {
                "class": "fish",
                "xn": "774.660313208;661.178848667",
                "yn": "1990.70379639;1953.07573184"
            },
            {
                "class": "fish",
                "xn": "909.046258059;766.298521084",
                "yn": "1985.92562947;1975.77202474"
            },
            {
                "class": "fish",
                "xn": "431.826836121;336.860768427",
                "yn": "2000.85740112;1938.14396019"
            },
            {
                "class": "fish",
                "xn": "213.82297003;223.379303886",
                "yn": "2106.5743444;1996.07923419"
            },
            {
                "class": "fish",
                "xn": "153.498612563;11.3481464541",
                "yn": "2222.4448924;2213.48582941"
            },
            {
                "class": "fish",
                "xn": "300.4272456;295.051807806",
                "yn": "2210.49947508;2123.29792865"
            },
            {
                "class": "fish",
                "xn": "368.516124325;306.39995426",
                "yn": "2213.48582941;2136.4378877"
            },
            {
                "class": "fish",
                "xn": "484.983943196;337.458039293",
                "yn": "2055.80632079;2047.44452866"
            },
            {
                "class": "fish",
                "xn": "679.694245513;503.499340042",
                "yn": "2099.40709401;2098.80982314"
            },
            {
                "class": "fish",
                "xn": "640.871639223;490.956651856",
                "yn": "2127.47882471;2168.0932436"
            },
            {
                "class": "fish",
                "xn": "613.397179387;496.33208965",
                "yn": "2234.39030972;2218.86126721"
            },
            {
                "class": "fish",
                "xn": "592.492699077;437.799544781",
                "yn": "2308.45189711;2278.58835381"
            },
            {
                "class": "fish",
                "xn": "439.591357379;351.792540077",
                "yn": "2373.5544215;2338.31544041"
            },
            {
                "class": "fish",
                "xn": "767.493062816;682.083328977",
                "yn": "2470.90957266;2392.06981835"
            },
            {
                "class": "fish",
                "xn": "933.534363565;781.230292734",
                "yn": "2153.75874281;2108.96342786"
            },
            {
                "class": "fish",
                "xn": "815.274732096;667.151557327",
                "yn": "2524.06667974;2584.3910372"
            },
            {
                "class": "fish",
                "xn": "179.778530667;195.90484405",
                "yn": "2328.75910655;2253.50297744"
            },
            {
                "class": "fish",
                "xn": "1121.07741549;963.995177731",
                "yn": "2564.08382776;2566.47291122"
            },
            {
                "class": "fish",
                "xn": "1306.23138395;1150.34368792",
                "yn": "2557.51384823;2549.15205611"
            },
            {
                "class": "fish",
                "xn": "1262.03333987;1098.38112258",
                "yn": "2427.90607031;2366.38717111"
            },
            {
                "class": "fish",
                "xn": "1079.86572574;941.896155689",
                "yn": "2276.19927034;2257.6838735"
            },
            {
                "class": "fish",
                "xn": "977.135136784;825.428336818",
                "yn": "2307.25735538;2282.171979"
            },
            {
                "class": "fish",
                "xn": "1090.01933046;955.633385607",
                "yn": "2379.52713016;2353.24721206"
            },
            {
                "class": "fish",
                "xn": "1244.71248475;1134.81464541",
                "yn": "2255.29479003;2201.54041209"
            },
            {
                "class": "fish",
                "xn": "1446.59003746;1332.51130206",
                "yn": "2345.4826908;2269.62929082"
            },
            {
                "class": "fish",
                "xn": "1637.71671458;1467.49451777",
                "yn": "2357.42810812;2347.2745034"
            },
            {
                "class": "fish",
                "xn": "1643.68942324;1468.09178864",
                "yn": "2205.12403729;2208.70766249"
            },
            {
                "class": "fish",
                "xn": "1610.83952561;1461.52180911",
                "yn": "2257.08660263;2200.34587036"
            },
            {
                "class": "fish",
                "xn": "1643.68942324;1486.00991462",
                "yn": "2101.79617747;2112.54705306"
            },
            {
                "class": "fish",
                "xn": "1371.33390835;1278.15965325",
                "yn": "2188.99772391;2151.96693021"
            },
            {
                "class": "fish",
                "xn": "1316.38498867;1192.15264855",
                "yn": "2133.45153337;2060.58448772"
            },
            {
                "class": "fish",
                "xn": "1383.87659653;1228.58617137",
                "yn": "2051.62542473;2022.95642316"
            },
            {
                "class": "fish",
                "xn": "1400.60018078;1244.11521389",
                "yn": "2008.62192237;2007.42738064"
            },
            {
                "class": "fish",
                "xn": "1179.01268949;1042.83493204",
                "yn": "1996.07923419;1976.36929561"
            },
            {
                "class": "fish",
                "xn": "993.261450166;893.517215543",
                "yn": "2078.5026137;2034.90184048"
            },
            {
                "class": "fish",
                "xn": "991.469637568;839.762837603",
                "yn": "1956.65935703;1927.99035546"
            },
            {
                "class": "fish",
                "xn": "1017.74955567;921.588946245",
                "yn": "1882.59776965;1838.99699643"
            },
            {
                "class": "fish",
                "xn": "1029.69497299;978.926949382",
                "yn": "1764.33813818;1695.65198859"
            },
            {
                "class": "fish",
                "xn": "1138.3982706;1009.38776355",
                "yn": "1705.80559331;1678.92840434"
            },
            {
                "class": "fish",
                "xn": "1169.45635564;1060.15578716",
                "yn": "1770.9081177;1726.11280275"
            },
            {
                "class": "fish",
                "xn": "1195.73627374;1049.40491157",
                "yn": "1843.17789249;1815.10616179"
            },
            {
                "class": "fish",
                "xn": "1216.04348319;1065.53122495",
                "yn": "1917.23947987;1906.48860429"
            },
            {
                "class": "fish",
                "xn": "1348.63761544;1232.76706743",
                "yn": "1914.85039641;1889.16774917"
            },
            {
                "class": "fish",
                "xn": "1429.26918235;1352.8185115",
                "yn": "1882.00049878;1990.70379639"
            },
            {
                "class": "fish",
                "xn": "1497.35806107;1402.98926424",
                "yn": "1925.601272;1830.03793344"
            },
            {
                "class": "fish",
                "xn": "1550.51516815;1401.19745165",
                "yn": "1869.45781059;1825.25976651"
            },
            {
                "class": "fish",
                "xn": "1634.73036025;1491.38535241",
                "yn": "1920.82310507;1923.21218853"
            },
            {
                "class": "fish",
                "xn": "1352.22124063;1253.67154774",
                "yn": "1770.31084684;1708.19467677"
            },
            {
                "class": "fish",
                "xn": "1283.53509104;1168.26181391",
                "yn": "1656.8293823;1625.1740264"
            },
            {
                "class": "fish",
                "xn": "1422.10193196;1303.84230049",
                "yn": "1622.78494293;1577.98962798"
            },
            {
                "class": "fish",
                "xn": "1508.10893666;1377.90388787",
                "yn": "1767.32449251;1719.54282323"
            },
            {
                "class": "fish",
                "xn": "1009.38776355;947.868864349",
                "yn": "1571.41964846;1493.17716501"
            },
            {
                "class": "fish",
                "xn": "991.469637568;902.476278533",
                "yn": "1459.72999652;1394.03020125"
            },
            {
                "class": "fish",
                "xn": "1108.5347273;999.831429692",
                "yn": "1437.63097447;1383.87659653"
            },
            {
                "class": "fish",
                "xn": "1110.92381077;1017.15228481",
                "yn": "1531.9997713;1497.95533194"
            },
            {
                "class": "fish",
                "xn": "1141.38462493;1038.05676512",
                "yn": "1366.55574142;1309.81500915"
            },
            {
                "class": "fish",
                "xn": "1229.18344224;1104.95110211",
                "yn": "1327.73313513;1289.5077997"
            },
            {
                "class": "fish",
                "xn": "1337.28946898;1183.79085642",
                "yn": "1537.97247996;1484.81537289"
            },
            {
                "class": "fish",
                "xn": "1365.36119969;1237.54523436",
                "yn": "1472.2726847;1422.69920282"
            },
            {
                "class": "fish",
                "xn": "1589.33777444;1423.89374456",
                "yn": "1536.77793823;1504.52531147"
            },
            {
                "class": "fish",
                "xn": "1518.85981225;1386.26568",
                "yn": "1419.11557763;1386.26568"
            },
            {
                "class": "fish",
                "xn": "1612.03406735;1486.60718549",
                "yn": "1444.200954;1386.26568"
            },
            {
                "class": "fish",
                "xn": "1504.52531147;1393.43293039",
                "yn": "1346.24853197;1283.53509104"
            },
            {
                "class": "fish",
                "xn": "1593.5186705;1475.8563099",
                "yn": "1275.77056979;1220.82165011"
            },
            {
                "class": "fish",
                "xn": "1190.36083595;1064.33668322",
                "yn": "1182.59631469;1131.23102021"
            },
            {
                "class": "fish",
                "xn": "1010.58230528;903.670820265",
                "yn": "1141.9818958;1089.42205959"
            },
            {
                "class": "fish",
                "xn": "1077.47664227;958.619739937",
                "yn": "1103.75656038;1075.68482967"
            },
            {
                "class": "fish",
                "xn": "1049.40491157;942.493426555",
                "yn": "1038.65403598;985.496928908"
            },
            {
                "class": "fish",
                "xn": "1132.42556194;1009.98503441",
                "yn": "1026.1113478;972.356969856"
            },
            {
                "class": "fish",
                "xn": "1109.13199817;1005.80413835",
                "yn": "984.302387176;948.466135215"
            },
            {
                "class": "fish",
                "xn": "1177.81814776;1043.43220291",
                "yn": "929.353467503;884.558152553"
            },
            {
                "class": "fish",
                "xn": "1408.36470204;1262.03333987",
                "yn": "1085.8384344;1049.40491157"
            },
            {
                "class": "fish",
                "xn": "1359.98576189;1248.89338082",
                "yn": "1024.3195352;961.008823401"
            },
            {
                "class": "fish",
                "xn": "1551.70970988;1422.10193196",
                "yn": "1050.00218244;971.162428124"
            },
            {
                "class": "fish",
                "xn": "1390.44657606;1292.49415403",
                "yn": "942.493426555;875.599089563"
            },
            {
                "class": "fish",
                "xn": "1566.04421066;1456.74364219",
                "yn": "936.520717895;889.933590347"
            },
            {
                "class": "fish",
                "xn": "1161.69183438;1065.53122495",
                "yn": "872.612735233;803.329314776"
            },
            {
                "class": "fish",
                "xn": "1279.95146585;1174.23452257",
                "yn": "839.165566736;783.022105332"
            },
            {
                "class": "fish",
                "xn": "1570.22510673;1450.17366266",
                "yn": "850.513713191;793.175710054"
            },
            {
                "class": "fish",
                "xn": "1009.38776355;891.725402945",
                "yn": "762.117625022;698.209642359"
            },
            {
                "class": "fish",
                "xn": "1020.13863914;919.199862781",
                "yn": "700.598725823;656.400681739"
            },
            {
                "class": "fish",
                "xn": "993.858721032;895.309028141",
                "yn": "624.745325841;571.588218766"
            },
            {
                "class": "fish",
                "xn": "1067.32303755;1075.08755881",
                "yn": "739.421332114;643.260722687"
            },
            {
                "class": "fish",
                "xn": "1197.52808634;1100.17293518",
                "yn": "616.383533717;581.144552622"
            },
            {
                "class": "fish",
                "xn": "1424.49101542;1288.31325797",
                "yn": "699.404184091;652.817056543"
            },
            {
                "class": "fish",
                "xn": "1354.01305323;1262.63061073",
                "yn": "777.049396672;745.99131164"
            },
            {
                "class": "fish",
                "xn": "1431.65826581;1341.47036505",
                "yn": "722.697747866;709.557788813"
            },
            {
                "class": "fish",
                "xn": "1433.45007841;1300.85594616",
                "yn": "634.898930563;600.854491201"
            },
            {
                "class": "fish",
                "xn": "1266.8115068;1195.13900288",
                "yn": "679.096974647;594.881782541"
            },
            {
                "class": "fish",
                "xn": "1600.08865003;1463.31362171",
                "yn": "700.001454957;674.916078585"
            },
            {
                "class": "fish",
                "xn": "1614.42315081;1489.59353982",
                "yn": "582.339094355;578.158198292"
            },
            {
                "class": "fish",
                "xn": "1546.33427209;1431.06099495",
                "yn": "459.898566824;441.383169977"
            },
            {
                "class": "fish",
                "xn": "1481.23174769;1364.16665795",
                "yn": "553.07282192;542.321946332"
            },
            {
                "class": "fish",
                "xn": "1328.33040599;1202.90352413",
                "yn": "490.35938099;462.287650288"
            },
            {
                "class": "fish",
                "xn": "1193.94446114;1064.33668322",
                "yn": "528.584716414;493.34573532"
            },
            {
                "class": "fish",
                "xn": "1090.01933046;988.483283238",
                "yn": "559.642801446;539.932862868"
            },
            {
                "class": "fish",
                "xn": "975.940595052;892.322673811",
                "yn": "581.144552622;479.608505402"
            },
            {
                "class": "fish",
                "xn": "1024.91680606;889.933590347",
                "yn": "445.564066039;442.577711709"
            },
            {
                "class": "fish",
                "xn": "1146.76006273;987.288741506",
                "yn": "302.219058198;301.024516466"
            },
            {
                "class": "fish",
                "xn": "1592.92139963;1441.21459967",
                "yn": "91.3824424987;115.273277139"
            },
            {
                "class": "fish",
                "xn": "1665.19117442;1566.64148153",
                "yn": "404.949647151;316.553558982"
            },
            {
                "class": "fish",
                "xn": "1874.83324839;1704.61105158",
                "yn": "107.508755881;102.133318087"
            },
            {
                "class": "fish",
                "xn": "1793.00713975;1663.39936182",
                "yn": "244.881055062;201.280281844"
            },
            {
                "class": "fish",
                "xn": "2070.14082157;1967.41023262",
                "yn": "138.566840913;96.1606094267"
            },
            {
                "class": "fish",
                "xn": "1993.69015072;1871.84689406",
                "yn": "317.150829848;281.314577888"
            },
            {
                "class": "fish",
                "xn": "1930.97670979;1801.96620274",
                "yn": "496.929360516;435.410461317"
            },
            {
                "class": "fish",
                "xn": "2263.65658216;2080.29442629",
                "yn": "542.919217198;528.584716414"
            },
            {
                "class": "fish",
                "xn": "1965.61842002;1895.14045783",
                "yn": "614.591721119;536.946508538"
            },
            {
                "class": "fish",
                "xn": "2273.21291601;2148.38330502",
                "yn": "634.898930563;595.479053407"
            },
            {
                "class": "fish",
                "xn": "2423.72517425;2275.00472861",
                "yn": "720.905935268;696.417829761"
            },
            {
                "class": "fish",
                "xn": "2390.87527662;2259.4756861",
                "yn": "836.179212406;786.008459662"
            },
            {
                "class": "fish",
                "xn": "2080.29442629;1909.47495862",
                "yn": "853.500067521;808.70475257"
            },
            {
                "class": "fish",
                "xn": "2106.5743444;1970.99385782",
                "yn": "957.425198205;918.602591915"
            },
            {
                "class": "fish",
                "xn": "2498.98130336;2380.12440103",
                "yn": "982.510574578;933.534363565"
            },
            {
                "class": "fish",
                "xn": "2534.81755532;2415.36338212",
                "yn": "876.196360429;829.60923288"
            },
            {
                "class": "fish",
                "xn": "1686.6929256;1572.61419019",
                "yn": "1277.56238238;1201.11171154"
            },
            {
                "class": "fish",
                "xn": "1926.79581373;1776.88082636",
                "yn": "1047.61309897;1002.81778402"
            },
            {
                "class": "fish",
                "xn": "1899.91862476;1770.31084684",
                "yn": "1336.09492725;1284.13236191"
            },
            {
                "class": "fish",
                "xn": "2015.78917277;1871.24962319",
                "yn": "1253.67154774;1241.72613042"
            },
            {
                "class": "fish",
                "xn": "2109.56069873;1980.55019167",
                "yn": "1367.75028315;1313.39863434"
            },
            {
                "class": "fish",
                "xn": "2247.53026878;2188.99772391",
                "yn": "1160.49729265;1063.14214149"
            },
            {
                "class": "fish",
                "xn": "2446.42146715;2351.45539946",
                "yn": "1067.92030842;1004.60959662"
            },
            {
                "class": "fish",
                "xn": "2521.67759627;2398.63979787",
                "yn": "1170.0536265;1114.50743596"
            },
            {
                "class": "fish",
                "xn": "2442.83784196;2280.97743727",
                "yn": "1333.10857292;1316.38498867"
            },
            {
                "class": "fish",
                "xn": "2462.54778054;2306.06281364",
                "yn": "1418.51830676;1389.84930519"
            },
            {
                "class": "fish",
                "xn": "2223.04216327;2088.05894755",
                "yn": "1458.53545478;1425.68555715"
            },
            {
                "class": "fish",
                "xn": "2009.21919324;1867.665998",
                "yn": "1508.70620753;1490.19081068"
            },
            {
                "class": "fish",
                "xn": "1872.44416492;1739.25276181",
                "yn": "1540.95883429;1518.26254138"
            },
            {
                "class": "fish",
                "xn": "1680.12294607;1553.50152248",
                "yn": "1622.18767207;1582.76779491"
            },
            {
                "class": "fish",
                "xn": "1691.47109253;1580.97598231",
                "yn": "1789.42351455;1758.36542952"
            },
            {
                "class": "fish",
                "xn": "1846.76151769;1695.65198859",
                "yn": "1699.83288465;1653.84302797"
            },
            {
                "class": "fish",
                "xn": "1962.03479483;1831.23247517",
                "yn": "1625.1740264;1606.06135869"
            },
            {
                "class": "fish",
                "xn": "1846.76151769;1707.00013504",
                "yn": "1834.2188295;1790.61805628"
            },
            {
                "class": "fish",
                "xn": "2210.49947508;2069.54355071",
                "yn": "1531.40250044;1498.55260281"
            },
            {
                "class": "fish",
                "xn": "2184.21955698;2053.41723732",
                "yn": "1598.29683743;1551.11243901"
            },
            {
                "class": "fish",
                "xn": "2172.87141052;2037.88819481",
                "yn": "1662.80209096;1609.64498388"
            },
            {
                "class": "fish",
                "xn": "2106.5743444;1971.59112868",
                "yn": "1731.48824055;1707.59740591"
            },
            {
                "class": "fish",
                "xn": "2150.77238848;1996.07923419",
                "yn": "1819.28705785;1795.39622321"
            },
            {
                "class": "fish",
                "xn": "2341.8990656;2207.51312075",
                "yn": "1794.79895234;1739.25276181"
            },
            {
                "class": "fish",
                "xn": "2418.94700732;2268.43474909",
                "yn": "1702.22196811;1663.99663269"
            },
            {
                "class": "fish",
                "xn": "2453.58871755;2308.45189711",
                "yn": "1639.50852718;1613.82587994"
            },
            {
                "class": "fish",
                "xn": "2482.25771912;2352.64994119",
                "yn": "1601.28319176;1561.26604374"
            },
            {
                "class": "fish",
                "xn": "2536.60936792;2418.94700732",
                "yn": "1539.16702169;1460.92453825"
            },
            {
                "class": "fish",
                "xn": "1695.05471772;1565.4469398",
                "yn": "1882.59776965;1846.16424682"
            },
            {
                "class": "fish",
                "xn": "1671.16388308;1555.29333508",
                "yn": "2029.52640268;2002.05194285"
            },
            {
                "class": "fish",
                "xn": "1812.11980746;1673.55296654",
                "yn": "1972.78567041;1927.3930846"
            },
            {
                "class": "fish",
                "xn": "1952.47846097;1834.2188295",
                "yn": "2038.48546567;1979.35564994"
            },
            {
                "class": "fish",
                "xn": "1804.95255707;1665.78844529",
                "yn": "2055.20904992;2049.83361213"
            },
            {
                "class": "fish",
                "xn": "2067.75173811;1920.2258342",
                "yn": "1874.23597752;1836.60791296"
            },
            {
                "class": "fish",
                "xn": "2188.99772391;2060.58448772",
                "yn": "1941.72758538;1933.96306412"
            },
            {
                "class": "fish",
                "xn": "2026.54004835;1930.97670979",
                "yn": "2010.41373497;1976.96656648"
            },
            {
                "class": "fish",
                "xn": "1900.51589563;1763.14359645",
                "yn": "2116.72794912;2119.71430345"
            },
            {
                "class": "fish",
                "xn": "1842.58062162;1698.63834292",
                "yn": "2200.34587036;2186.01136958"
            },
            {
                "class": "fish",
                "xn": "2107.76888613;1981.14746254",
                "yn": "2080.29442629;2043.2636326"
            },
            {
                "class": "fish",
                "xn": "2433.2815081;2314.42460577",
                "yn": "1901.11316649;1849.15060115"
            },
            {
                "class": "fish",
                "xn": "2366.38717111;2202.73495383",
                "yn": "1932.17125152;1902.90497909"
            },
            {
                "class": "fish",
                "xn": "2326.37002309;2169.28778533",
                "yn": "2006.83010978;1976.96656648"
            },
            {
                "class": "fish",
                "xn": "2495.39767817;2357.42810812",
                "yn": "2059.38994598;2002.05194285"
            },
            {
                "class": "fish",
                "xn": "2499.57857423;2376.54077583",
                "yn": "2190.7895365;2119.11703258"
            },
            {
                "class": "fish",
                "xn": "2550.94386871;2396.25071441",
                "yn": "2022.35915229;1973.98021215"
            },
            {
                "class": "fish",
                "xn": "2325.17548136;2160.32872234",
                "yn": "2258.28114436;2313.23006404"
            },
            {
                "class": "fish",
                "xn": "1949.49210664;1760.15724212",
                "yn": "2365.78990024;2388.48619315"
            },
            {
                "class": "fish",
                "xn": "1704.01378071;1577.98962798",
                "yn": "2471.50684353;2473.89592699"
            },
            {
                "class": "fish",
                "xn": "1772.6999303;1649.6621319",
                "yn": "2579.61287027;2532.42847186"
            },
            {
                "class": "fish",
                "xn": "2018.7755271;1851.53968461",
                "yn": "2452.39417581;2470.3123018"
            },
            {
                "class": "fish",
                "xn": "2150.17511762;1991.89833813",
                "yn": "2481.66044825;2497.78676163"
            },
            {
                "class": "fish",
                "xn": "2108.96342786;1950.08937751",
                "yn": "2544.97116005;2542.58207658"
            },
            {
                "class": "fish",
                "xn": "2292.32558373;2129.27063731",
                "yn": "2548.55478524;2573.04289075"
            },
            {
                "class": "fish",
                "xn": "2043.2636326;1883.79231138",
                "yn": "2318.00823096;2291.72831286"
            },
            {
                "class": "fish",
                "xn": "2641.13176947;2524.6639506",
                "yn": "2295.90920892;2236.77939319"
            },
            {
                "class": "fish",
                "xn": "3280.80886696;3103.41941976",
                "yn": "2434.47604983;2400.43161047"
            },
            {
                "class": "fish",
                "xn": "3240.79171894;3123.7266292",
                "yn": "2312.63279317;2337.12089868"
            },
            {
                "class": "fish",
                "xn": "3364.4267882;3258.70984492",
                "yn": "2347.87177426;2308.45189711"
            },
            {
                "class": "fish",
                "xn": "3093.8630859;2927.82178515",
                "yn": "2288.74195853;2316.21641837"
            },
            {
                "class": "fish",
                "xn": "2826.8830088;2719.97152379",
                "yn": "2300.68737585;2233.79303886"
            },
            {
                "class": "fish",
                "xn": "2625.00545609;2512.71853328",
                "yn": "2190.7895365;2111.35251133"
            },
            {
                "class": "fish",
                "xn": "2749.23779622;2633.36724821",
                "yn": "2184.81682784;2157.34236801"
            },
            {
                "class": "fish",
                "xn": "2857.94109383;2722.95787812",
                "yn": "2116.13067825;2071.93263417"
            },
            {
                "class": "fish",
                "xn": "3250.3480528;3146.42292211",
                "yn": "2067.75173811;1992.49560899"
            },
            {
                "class": "fish",
                "xn": "3028.76056151;2919.45999303",
                "yn": "2048.6390704;2002.64921371"
            },
            {
                "class": "fish",
                "xn": "2847.19021824;2738.48692063",
                "yn": "1927.99035546;1865.8741854"
            },
            {
                "class": "fish",
                "xn": "2613.06003877;2478.67409392",
                "yn": "1904.09952082;1849.74787202"
            },
            {
                "class": "fish",
                "xn": "3089.68218984;2990.53522609",
                "yn": "1906.48860429;1843.17789249"
            },
            {
                "class": "fish",
                "xn": "2889.59644973;2764.16956787",
                "yn": "1837.20518383;1776.2835555"
            },
            {
                "class": "fish",
                "xn": "2991.72976782;2858.5383647",
                "yn": "1733.87732401;1668.17752875"
            },
            {
                "class": "fish",
                "xn": "2733.11148284;2573.04289075",
                "yn": "1673.55296654;1641.30033978"
            },
            {
                "class": "fish",
                "xn": "2670.39804191;2546.16570178",
                "yn": "1532.59704217;1459.13272565"
            },
            {
                "class": "fish",
                "xn": "2834.05025919;2693.69160568",
                "yn": "1476.45358076;1447.18730833"
            },
            {
                "class": "fish",
                "xn": "2939.76720247;2811.35396628",
                "yn": "1606.65862955;1563.05785633"
            },
            {
                "class": "fish",
                "xn": "2585.58557893;2470.90957266",
                "yn": "1302.05048789;1244.11521389"
            },
            {
                "class": "fish",
                "xn": "3692.92576451;3613.48873933",
                "yn": "2509.73217895;2431.4896955"
            }
        ],
        "class": "image",
        "filename": "Dropbox\\4_Students\\Apollonia_Landes\\1_To_do\\Molly_vs_Gambusa_Finaler Ordner\\IMG_7976.jpg"
    }
]
