[
    {
        "annotations": [
            {
                "class": "fish",
                "xn": "95.1631670805;239.171145583",
                "yn": "425.286720139;291.384564689"
            },
            {
                "class": "fish",
                "xn": "64.0035460011;254.329880162",
                "yn": "574.347610167;510.344064166"
            },
            {
                "class": "fish",
                "xn": "357.072414532;149.060890029",
                "yn": "727.619259801;706.565461775"
            },
            {
                "class": "fish",
                "xn": "766.358248171;544.87229293",
                "yn": "704.881157933;644.246219616"
            },
            {
                "class": "fish",
                "xn": "926.367113173;1002.16078607",
                "yn": "726.77710788;616.455206221"
            },
            {
                "class": "fish",
                "xn": "1053.53205325;1144.48446073",
                "yn": "819.413819198;650.141283063"
            },
            {
                "class": "fish",
                "xn": "1341.54801026;1275.86016042",
                "yn": "763.831792407;630.771788879"
            },
            {
                "class": "fish",
                "xn": "1106.58762428;1309.54623726",
                "yn": "477.500139245;539.819381404"
            },
            {
                "class": "fish",
                "xn": "1264.91218544;1139.4315492",
                "yn": "394.96925098;458.13064506"
            },
            {
                "class": "fish",
                "xn": "1064.48002823;950.789518884",
                "yn": "308.22760311;400.022162507"
            },
            {
                "class": "fish",
                "xn": "993.739266859;802.570780776",
                "yn": "282.120893557;321.702033847"
            },
            {
                "class": "fish",
                "xn": "985.317747648;755.410273197",
                "yn": "173.48329574;253.487728241"
            },
            {
                "class": "fish",
                "xn": "573.505458246;383.179124085",
                "yn": "895.207492094;977.738380358"
            },
            {
                "class": "fish",
                "xn": "784.043438513;828.677490329",
                "yn": "1048.47914173;882.575213278"
            },
            {
                "class": "fish",
                "xn": "965.106101542;1071.2172436",
                "yn": "1042.58407828;943.210151595"
            },
            {
                "class": "fish",
                "xn": "1216.90952594;1152.90597994",
                "yn": "980.264836121;1156.27458762"
            },
            {
                "class": "fish",
                "xn": "308.22760311;505.29115264",
                "yn": "1179.85484141;1082.16521857"
            },
            {
                "class": "fish",
                "xn": "364.651781822;414.338745165",
                "yn": "1300.28256613;1157.95889147"
            },
            {
                "class": "fish",
                "xn": "325.912793453;281.278741636",
                "yn": "1372.70763134;1242.17408357"
            },
            {
                "class": "fish",
                "xn": "53.0555710272;234.960385978",
                "yn": "1549.55953476;1438.39548118"
            },
            {
                "class": "fish",
                "xn": "4.21075960533;28.6331653163",
                "yn": "1465.34434266;1300.28256613"
            },
            {
                "class": "fish",
                "xn": "451.393429692;223.170259083",
                "yn": "1519.2420656;1648.09130953"
            },
            {
                "class": "fish",
                "xn": "368.020389506;155.798105397",
                "yn": "1655.67067682;1736.51726124"
            },
            {
                "class": "fish",
                "xn": "537.29292564;337.702920348",
                "yn": "1596.72004234;1728.93789395"
            },
            {
                "class": "fish",
                "xn": "792.464957724;1008.89800144",
                "yn": "1712.93700745;1617.77384037"
            },
            {
                "class": "fish",
                "xn": "997.950026464;960.053190016",
                "yn": "1811.46878221;1646.40700569"
            },
            {
                "class": "fish",
                "xn": "1209.33015865;1170.59117028",
                "yn": "1498.18826758;1371.86547942"
            },
            {
                "class": "fish",
                "xn": "1330.60003529;1259.01712199",
                "yn": "1757.57105927;1592.50928274"
            },
            {
                "class": "fish",
                "xn": "1237.12117205;1124.27281462",
                "yn": "2104.53765075;1948.73954535"
            },
            {
                "class": "fish",
                "xn": "1047.63698981;1065.32218015",
                "yn": "1998.42650869;1888.10460703"
            },
            {
                "class": "fish",
                "xn": "931.4200247;895.207492094",
                "yn": "1896.52612624;1759.25536311"
            },
            {
                "class": "fish",
                "xn": "917.945593963;791.622805803",
                "yn": "2156.75106985;2032.11258553"
            },
            {
                "class": "fish",
                "xn": "1165.53825876;930.577872779",
                "yn": "2181.17347556;2234.22904659"
            },
            {
                "class": "fish",
                "xn": "1189.96066447;974.369772674",
                "yn": "2294.86398491;2294.02183299"
            },
            {
                "class": "fish",
                "xn": "744.462298223;525.502798746",
                "yn": "2123.90714493;2105.37980267"
            },
            {
                "class": "fish",
                "xn": "826.151034566;602.980775484",
                "yn": "2206.43803319;2197.17436206"
            },
            {
                "class": "fish",
                "xn": "741.93584246;517.081279535",
                "yn": "2276.33664264;2246.86132541"
            },
            {
                "class": "fish",
                "xn": "480.868746929;265.277855136",
                "yn": "2260.33575614;2205.59588127"
            },
            {
                "class": "fish",
                "xn": "302.332539663;146.534434266",
                "yn": "2327.70790983;2223.28107162"
            },
            {
                "class": "fish",
                "xn": "1251.4377547;1025.74103986",
                "yn": "2448.97778646;2459.08360951"
            },
            {
                "class": "fish",
                "xn": "810.992299987;606.349383168",
                "yn": "2441.39841917;2433.81905188"
            },
            {
                "class": "fish",
                "xn": "407.601529796;271.172918583",
                "yn": "2451.50424222;2365.60474628"
            },
            {
                "class": "fish",
                "xn": "373.915452954;136.428611213",
                "yn": "2544.14095354;2494.4539902"
            },
            {
                "class": "fish",
                "xn": "1440.07978502;1282.59737578",
                "yn": "2314.23347909;2294.86398491"
            },
            {
                "class": "fish",
                "xn": "1394.60358129;1313.75699686",
                "yn": "2145.80309488;2006.8480279"
            },
            {
                "class": "fish",
                "xn": "1902.42118969;1710.41055169",
                "yn": "2078.43094119;2137.38157567"
            },
            {
                "class": "fish",
                "xn": "2113.80132188;1899.89473393",
                "yn": "2294.02183299;2207.28018512"
            },
            {
                "class": "fish",
                "xn": "2219.07031201;1999.26866061",
                "yn": "2180.33132364;2128.96005646"
            },
            {
                "class": "fish",
                "xn": "1688.51460174;1575.66624432",
                "yn": "1933.58081077;1795.46789571"
            },
            {
                "class": "fish",
                "xn": "2274.6523388;2036.32334514",
                "yn": "1743.25447661;1785.36207266"
            },
            {
                "class": "fish",
                "xn": "2140.75018335;2161.80398138",
                "yn": "1638.8276384;1529.34788866"
            },
            {
                "class": "fish",
                "xn": "2233.38689467;2287.28461762",
                "yn": "1649.77561337;1498.18826758"
            },
            {
                "class": "fish",
                "xn": "2346.23525209;2358.86753091",
                "yn": "1741.57017277;1616.08953653"
            },
            {
                "class": "fish",
                "xn": "2154.22461409;2293.17968106",
                "yn": "1493.13535605;1381.12915055"
            },
            {
                "class": "fish",
                "xn": "1977.37271066;2114.6434738",
                "yn": "1548.71738284;1404.70940434"
            },
            {
                "class": "fish",
                "xn": "1942.00232998;1729.78004587",
                "yn": "1329.75788336;1294.38750268"
            },
            {
                "class": "fish",
                "xn": "1729.78004587;1584.08776353",
                "yn": "1585.77206737;1501.55687526"
            },
            {
                "class": "fish",
                "xn": "1544.50662324;1387.024214",
                "yn": "1533.55864826;1402.18294858"
            },
            {
                "class": "fish",
                "xn": "1458.60712729;1319.65206031",
                "yn": "1666.61865179;1523.45282521"
            },
            {
                "class": "fish",
                "xn": "1697.77827287;1486.39814068",
                "yn": "1658.19713258;1743.25447661"
            },
            {
                "class": "fish",
                "xn": "2288.12676954;2090.22106809",
                "yn": "1083.00737049;1282.59737578"
            },
            {
                "class": "fish",
                "xn": "2047.27132011;1854.41853019",
                "yn": "1128.48357423;1072.05939552"
            },
            {
                "class": "fish",
                "xn": "1717.98991898;1568.92902895",
                "yn": "1175.64408181;1131.01002999"
            },
            {
                "class": "fish",
                "xn": "1496.50396374;1492.29320413",
                "yn": "887.628124804;736.040779012"
            },
            {
                "class": "fish",
                "xn": "1758.41321119;1557.13890205",
                "yn": "812.676603829;893.523188252"
            },
            {
                "class": "fish",
                "xn": "1914.21131658;1834.20688408",
                "yn": "880.890909436;804.255084619"
            },
            {
                "class": "fish",
                "xn": "2306.6541118;2167.69904483",
                "yn": "960.053190016;886.785972883"
            },
            {
                "class": "fish",
                "xn": "2390.02715199;2168.54119675",
                "yn": "747.830905907;845.520528751"
            },
            {
                "class": "fish",
                "xn": "1781.99346498;1595.87789042",
                "yn": "499.396089192;442.12975856"
            },
            {
                "class": "fish",
                "xn": "1346.60092179;1574.82409239",
                "yn": "255.172032083;240.855449425"
            },
            {
                "class": "fish",
                "xn": "1784.51992074;1954.6346088",
                "yn": "220.643803319;119.585572791"
            },
            {
                "class": "fish",
                "xn": "1999.26866061;2203.91157743",
                "yn": "245.06620903;188.642030319"
            },
            {
                "class": "fish",
                "xn": "1420.71029084;1187.4342087",
                "yn": "50.529115264;37.0546845269"
            },
            {
                "class": "fish",
                "xn": "2416.97601346;2222.43891969",
                "yn": "661.931409958;597.927863957"
            },
            {
                "class": "fish",
                "xn": "2513.82348438;2395.92221543",
                "yn": "485.921658455;412.654441323"
            },
            {
                "class": "fish",
                "xn": "2724.36146465;2725.20361657",
                "yn": "443.814062402;273.699374347"
            },
            {
                "class": "fish",
                "xn": "3065.43299268;3014.90387742",
                "yn": "597.927863957;517.923431456"
            },
            {
                "class": "fish",
                "xn": "2507.92842094;2300.75904835",
                "yn": "897.733947857;978.580532279"
            },
            {
                "class": "fish",
                "xn": "2677.20095707;2714.2556416",
                "yn": "962.579645779;789.096350039"
            },
            {
                "class": "fish",
                "xn": "2802.68159331;2598.03867649",
                "yn": "1482.18738108;1602.61510579"
            },
            {
                "class": "fish",
                "xn": "2366.4468982;2600.56513225",
                "yn": "1827.46966871;1735.67510932"
            },
            {
                "class": "fish",
                "xn": "2776.57488376;2539.93019394",
                "yn": "1839.25979561;1844.31270714"
            },
            {
                "class": "fish",
                "xn": "2662.04222249;2439.71411533",
                "yn": "1968.95119145;1926.8435954"
            },
            {
                "class": "fish",
                "xn": "2529.82437088;2299.91689643",
                "yn": "2107.06410651;2083.48385272"
            },
            {
                "class": "fish",
                "xn": "2984.58640826;2831.31475863",
                "yn": "2178.6470198;2032.11258553"
            },
            {
                "class": "fish",
                "xn": "3113.43565218;2961.84830639",
                "yn": "2022.00676248;1925.15929156"
            },
            {
                "class": "fish",
                "xn": "2849.84210089;2705.83412239",
                "yn": "2319.28639062;2223.28107162"
            },
            {
                "class": "fish",
                "xn": "2618.2503226;2491.08538251",
                "yn": "2393.39575967;2291.49537722"
            },
            {
                "class": "fish",
                "xn": "2495.29614212;2298.23259259",
                "yn": "2510.4548767;2500.34905365"
            },
            {
                "class": "fish",
                "xn": "3388.81933037;3258.28578261",
                "yn": "2539.08804202;2402.6594308"
            },
            {
                "class": "fish",
                "xn": "3394.71439382;3233.8633769",
                "yn": "2350.4460117;2283.91600993"
            },
            {
                "class": "fish",
                "xn": "3408.18882456;3249.8642634",
                "yn": "2230.86043891;2151.69815832"
            },
            {
                "class": "fish",
                "xn": "3372.81844387;3169.01767897",
                "yn": "2023.69106632;1952.10815303"
            },
            {
                "class": "fish",
                "xn": "3724.83794688;3525.24794158",
                "yn": "2082.6417008;2063.27220661"
            },
            {
                "class": "fish",
                "xn": "3708.83706038;3525.24794158",
                "yn": "1928.52789924;1813.15308606"
            },
            {
                "class": "fish",
                "xn": "3619.56895674;3421.66325529",
                "yn": "1638.8276384;1559.66535782"
            },
            {
                "class": "fish",
                "xn": "3413.24173608;3234.70552882",
                "yn": "1796.31004763;1768.51903424"
            },
            {
                "class": "fish",
                "xn": "3216.17818655;3267.54945374",
                "yn": "1425.76320237;1274.17585657"
            },
            {
                "class": "fish",
                "xn": "3531.14300503;3427.55831874",
                "yn": "1328.91573144;1176.48623373"
            },
            {
                "class": "fish",
                "xn": "3751.78680835;3677.6774393",
                "yn": "1307.0197815;1169.74901836"
            },
            {
                "class": "fish",
                "xn": "3599.35731064;3673.46667969",
                "yn": "928.051417015;781.51698275"
            },
            {
                "class": "fish",
                "xn": "3316.39426516;3397.24084958",
                "yn": "813.51875575;666.142169564"
            },
            {
                "class": "fish",
                "xn": "3456.19148406;3528.61654927",
                "yn": "494.343177666;635.824700405"
            },
            {
                "class": "fish",
                "xn": "3737.47022569;3558.93401843",
                "yn": "469.920771955;442.12975856"
            },
            {
                "class": "fish",
                "xn": "133.0;192.0",
                "yn": "1715.0;1932.0"
            },
            {
                "class": "fish",
                "xn": "272.0;488.0",
                "yn": "1905.0;1826.0"
            }
        ],
        "class": "image",
        "filename": "..\\IMG_6014.jpg"
    }
]
